opensearcheval/__init__.py
opensearcheval/cli.py
opensearcheval/main.py
opensearcheval/api/main.py
opensearcheval/api/routes/__init__.py
opensearcheval/api/routes/analytics.py
opensearcheval/api/routes/dashboard.py
opensearcheval/core/agent.py
opensearcheval/core/config.py
opensearcheval/core/experiment.py
opensearcheval/core/metrics.py
opensearcheval/data/connectors/__init__.py
opensearcheval/data/connectors/databricks.py
opensearcheval/data/connectors/spark.py
opensearcheval/data/connectors/sql.py
opensearcheval/data/processors/__init__.py
opensearcheval/data/processors/experiment_data.py
opensearcheval/data/processors/interaction_data.py
opensearcheval/data/processors/relevance_judgments.py
opensearcheval/data/processors/search_logs.py
opensearcheval/ml/embeddings.py
opensearcheval/ml/llm_judge.py
opensearcheval/ml/models.py
opensearcheval/tests/__init__.py
opensearcheval/tests/conftest.py
opensearcheval/tests/test_core_metrics.py
opensearcheval/tests/test_package.py
opensearcheval/ui/app.py
opensearcheval/ui/static/css/dashboard.css
opensearcheval/ui/static/css/styles.css
opensearcheval/ui/static/js/app.js
opensearcheval/ui/static/js/dashboard.js
opensearcheval/ui/templates/base.html
opensearcheval/ui/templates/dashboard.html
opensearcheval/ui/templates/index.html
opensearcheval/utils/stats.py
opensearcheval/utils/visualization.py
opensearcheval-1.0.2.dist-info/licenses/LICENSE
opensearcheval-1.0.2.dist-info/METADATA
opensearcheval-1.0.2.dist-info/WHEEL
opensearcheval-1.0.2.dist-info/entry_points.txt
opensearcheval-1.0.2.dist-info/top_level.txt
opensearcheval-1.0.2.dist-info/RECORD
