Metadata-Version: 2.4
Name: opensearcheval
Version: 1.0.2
Summary: A comprehensive search evaluation platform with agent architecture and MLX integration
Home-page: https://github.com/llamasearchai/OpenSearchEval
Author: Nik Jois
Author-email: Nik Jois <nikjois@llamasearch.ai>
Maintainer: Nik Jois
Maintainer-email: nikjois@llamasearch.ai
License: MIT
Project-URL: Homepage, https://github.com/llamasearchai/OpenSearchEval
Project-URL: Documentation, https://opensearcheval.readthedocs.io/
Project-URL: Repository, https://github.com/llamasearchai/OpenSearchEval
Project-URL: Bug Tracker, https://github.com/llamasearchai/OpenSearchEval/issues
Project-URL: Changelog, https://github.com/llamasearchai/OpenSearchEval/blob/main/CHANGELOG.md
Keywords: search,evaluation,a/b testing,mlx,llm,machine learning,information retrieval,search quality,metrics,analytics,experiment,ranking,click-through rate,precision,recall,ndcg,mrr,agent architecture,fastapi,dashboard,visualization
Platform: any
Classifier: Development Status :: 5 - Production/Stable
Classifier: Intended Audience :: Developers
Classifier: Intended Audience :: Science/Research
Classifier: Intended Audience :: Information Technology
Classifier: License :: OSI Approved :: MIT License
Classifier: Operating System :: OS Independent
Classifier: Programming Language :: Python :: 3
Classifier: Programming Language :: Python :: 3.9
Classifier: Programming Language :: Python :: 3.10
Classifier: Programming Language :: Python :: 3.11
Classifier: Programming Language :: Python :: 3.12
Classifier: Topic :: Scientific/Engineering :: Artificial Intelligence
Classifier: Topic :: Software Development :: Libraries :: Python Modules
Classifier: Topic :: Software Development :: Quality Assurance
Classifier: Topic :: Software Development :: Testing
Classifier: Topic :: Internet :: WWW/HTTP :: Indexing/Search
Classifier: Topic :: Database :: Database Engines/Servers
Classifier: Typing :: Typed
Requires-Python: >=3.9
License-File: LICENSE
Requires-Dist: pydantic>=2.4.0
Requires-Dist: pydantic-settings>=2.0.0
Requires-Dist: python-dotenv>=1.0.0
Requires-Dist: fastapi>=0.104.0
Requires-Dist: uvicorn[standard]>=0.23.2
Requires-Dist: httpx>=0.24.0
Requires-Dist: pandas>=2.0.0
Requires-Dist: numpy>=1.24.0
Requires-Dist: scikit-learn>=1.3.0
Requires-Dist: mlx>=0.0.5
Requires-Dist: matplotlib>=3.7.0
Requires-Dist: seaborn>=0.12.0
Requires-Dist: sqlalchemy>=2.0.0
Requires-Dist: pyspark>=3.4.0
Requires-Dist: flask>=2.3.0
Requires-Dist: flask-cors>=4.0.0
Requires-Dist: plotly>=5.14.0
Requires-Dist: dash>=2.11.0
Requires-Dist: dash-bootstrap-components>=1.4.0
Requires-Dist: click>=8.0.0
Requires-Dist: rich>=13.0.0
Requires-Dist: typer>=0.9.0
Requires-Dist: redis>=4.5.0
Requires-Dist: transformers>=4.30.0
Requires-Dist: torch>=2.0.0
Requires-Dist: openai>=1.0.0
Provides-Extra: dev
Requires-Dist: pytest>=7.4.0; extra == "dev"
Requires-Dist: pytest-asyncio>=0.21.0; extra == "dev"
Requires-Dist: pytest-cov>=4.1.0; extra == "dev"
Requires-Dist: pytest-mock>=3.11.0; extra == "dev"
Requires-Dist: pytest-xdist>=3.3.0; extra == "dev"
Requires-Dist: pytest-benchmark>=4.0.0; extra == "dev"
Requires-Dist: coverage>=7.2.0; extra == "dev"
Requires-Dist: black>=23.3.0; extra == "dev"
Requires-Dist: isort>=5.12.0; extra == "dev"
Requires-Dist: flake8>=6.0.0; extra == "dev"
Requires-Dist: mypy>=1.3.0; extra == "dev"
Requires-Dist: pre-commit>=3.3.0; extra == "dev"
Requires-Dist: bandit>=1.7.5; extra == "dev"
Requires-Dist: sphinx>=7.0.0; extra == "dev"
Requires-Dist: sphinx-rtd-theme>=1.2.0; extra == "dev"
Requires-Dist: jupyter>=1.0.0; extra == "dev"
Requires-Dist: notebook>=6.5.0; extra == "dev"
Provides-Extra: gpu
Requires-Dist: torch[cuda]>=2.0.0; extra == "gpu"
Requires-Dist: tensorflow-gpu>=2.13.0; extra == "gpu"
Requires-Dist: cupy-cuda12x>=12.0.0; extra == "gpu"
Provides-Extra: all
Requires-Dist: torch[cuda]>=2.0.0; extra == "all"
Requires-Dist: tensorflow-gpu>=2.13.0; extra == "all"
Requires-Dist: cupy-cuda12x>=12.0.0; extra == "all"
Dynamic: author
Dynamic: home-page
Dynamic: license-file
Dynamic: maintainer
Dynamic: maintainer-email
Dynamic: platform
Dynamic: requires-python
